Workbook

Sheet Hoja1
A3: Cuenta de COMPRA
A4: Género | B4: 2024 | C4: 2025 | D4: Total general
A5: Masculino | B5: 859 | C5: 511 | D5: 1370
A6: Femenino | B6: 2243 | C6: 1387 | D6: 3630
A7: Total general | B7: 3102 | C7: 1898 | D7: 5000
A19: Tipo de pago | B19: Promedio de TOTAL A PAGAR
A20: Efectivo | B20: 94.120794
A21: Tarjeta de crédito | B21: 82.938656
A22: Tarjeta Deprati | B22: 94.799386
A23: Total general | B23: 90.222958
A36: Clientes | B36: Edades.
A37: Adultos jóvenes 18 - 35 años | B37: 1856
A38: Adultos mayores 36 años en adelante | B38: 3144
A39: Total general | B39: 5000

Sheet Tienda
A1: ID CLIENTE | B1: GENERO | C1: EDAD | D1: CATEGORIA_EDAD | E1: COMPRA | F1: COLOR | G1: MARCA | H1: CODIGO DE ROPA | I1: FECHA DE COMPRA | J1: AÑO DE COMPRA | K1: PRECIO | L1: DESCUENTO | M1: TOTAL A PAGAR | N1: TIPO DE PAGO | O1: DIFERIDO | P1: FECHA DE CORTE | Q1: MESES DIFERIDO
A2: DEP-A0-0023 | B2: Femenino | C2: 28 | D2: =IF(Tabla1[[#This Row],[EDAD]]<=35,"Adultos jóvenes 18 - 35 años",IF(C2>=36,"Adultos mayores 36 años en adelante")) -> Adultos jóvenes 18 - 35 años | E2: Pantalón | F2: Gris | G2: Adidas | H2: MER-A0-0023 | I2: 45312 | J2: =YEAR(Tabla1[[#This Row],[FECHA DE COMPRA]]) -> 2024 | K2: 11.39 | L2: 0.3 | M2: =Tienda!$K3-Tienda!$K3*Tienda!$L3 -> 21.368 | N2: Efectivo | O2: No | P2: 45312 | Q2: 0
A3: DEP-A0-1736 | B3: Femenino | C3: 24 | D3: =IF(Tabla1[[#This Row],[EDAD]]<=35,"Adultos jóvenes 18 - 35 años",IF(C3>=36,"Adultos mayores 36 años en adelante")) -> Adultos jóvenes 18 - 35 años | E3: Blusa | F3: Verde | G3: Zara | H3: MER-A0-1736 | I3: 45312 | J3: =YEAR(Tabla1[[#This Row],[FECHA DE COMPRA]]) -> 2024 | K3: 26.71 | L3: 0.2 | M3: =Tienda!$K4-Tienda!$K4*Tienda!$L4 -> 49.994 | N3: Efectivo | O3: No | P3: 45312 | Q3: 0
A4: DEP-A0-3526 | B4: Masculino | C4: 31 | D4: =IF(Tabla1[[#This Row],[EDAD]]<=35,"Adultos jóvenes 18 - 35 años",IF(C4>=36,"Adultos mayores 36 años en adelante")) -> Adultos jóvenes 18 - 35 años | E4: Camisa | F4: Blanco | G4: Mango | H4: MER-A0-3526 | I4: 45313 | J4: =YEAR(Tabla1[[#This Row],[FECHA DE COMPRA]]) -> 2024 | K4: 71.42 | L4: 0.3 | M4: =Tienda!$K5-Tienda!$K5*Tienda!$L5 -> 48.111 | N4: Efectivo | O4: No | P4: 45313 | Q4: 0
A5: DEP-A0-4042 | B5: Femenino | C5: 30 | D5: =IF(Tabla1[[#This Row],[EDAD]]<=35,"Adultos jóvenes 18 - 35 años",IF(C5>=36,"Adultos mayores 36 años en adelante")) -> Adultos jóvenes 18 - 35 años | E5: Falda | F5: Blanco | G5: Mango | H5: MER-A0-4042 | I5: 45314 | J5: =YEAR(Tabla1[[#This Row],[FECHA DE COMPRA]]) -> 2024 | K5: 68.73 | L5: 0.3 | M5: =Tienda!$K7-Tienda!$K7*Tienda!$L7 -> 18.16 | N5: Efectivo | O5: No | P5: 45314 | Q5: 0
A6: DEP-A0-0519 | B6: Femenino | C6: 22 | D6: =IF(Tabla1[[#This Row],[EDAD]]<=35,"Adultos jóvenes 18 - 35 años",IF(C6>=36,"Adultos mayores 36 años en adelante")) -> Adultos jóvenes 18 - 35 años | E6: Blusa | F6: Verde | G6: Nike | H6: MER-A0-0519 | I6: 45318 | J6: =YEAR(Tabla1[[#This Row],[FECHA DE COMPRA]]) -> 2024 | K6: 10.65 | L6: 0 | M6: =Tienda!$K12-Tienda!$K12*Tienda!$L12 -> 19.75 | N6: Efectivo | O6: No | P6: 45318 | Q6: 0
A7: DEP-A0-4183 | B7: Masculino | C7: 29 | D7: =IF(Tabla1[[#This Row],[EDAD]]<=35,"Adultos jóvenes 18 - 35 años",IF(C7>=36,"Adultos mayores 36 años en adelante")) -> Adultos jóvenes 18 - 35 años | E7: Chaqueta | F7: Negro | G7: Mango | H7: MER-A0-4183 | I7: 45319 | J7: =YEAR(Tabla1[[#This Row],[FECHA DE COMPRA]]) -> 2024 | K7: 22.7 | L7: 0.2 | M7: =Tienda!$K16-Tienda!$K16*Tienda!$L16 -> 128.023 | N7: Efectivo | O7: No | P7: 45319 | Q7: 0
A8: DEP-A0-4126 | B8: Femenino | C8: 22 | D8: =IF(Tabla1[[#This Row],[EDAD]]<=35,"Adultos jóvenes 18 - 35 años",IF(C8>=36,"Adultos mayores 36 años en adelante")) -> Adultos jóvenes 18 - 35 años | E8: Zapatos | F8: Verde | G8: Nike | H8: MER-A0-4126 | I8: 45320 | J8: =YEAR(Tabla1[[#This Row],[FECHA DE COMPRA]]) -> 2024 | K8: 110 | L8: 0.1 | M8: =Tienda!$K17-Tienda!$K17*Tienda!$L17 -> 133.384 | N8: Efectivo | O8: No | P8: 45320 | Q8: 0
A9: DEP-A0-0084 | B9: Femenino | C9: 24 | D9: =IF(Tabla1[[#This Row],[EDAD]]<=35,"Adultos jóvenes 18 - 35 años",IF(C9>=36,"Adultos mayores 36 años en adelante")) -> Adultos jóvenes 18 - 35 años | E9: Vestido | F9: Verde | G9: Nike | H9: MER-A0-0084 | I9: 45320 | J9: =YEAR(Tabla1[[#This Row],[FECHA DE COMPRA]]) -> 2024 | K9: 125.71 | L9: 0.1 | M9: =Tienda!$K18-Tienda!$K18*Tienda!$L18 -> 28.96 | N9: Efectivo | O9: No | P9: 45320 | Q9: 0
A10: DEP-A0-1801 | B10: Femenino | C10: 20 | D10: =IF(Tabla1[[#This Row],[EDAD]]<=35,"Adultos jóvenes 18 - 35 años",IF(C10>=36,"Adultos mayores 36 años en adelante")) -> Adultos jóvenes 18 - 35 años | E10: Zapatos | F10: Amarillo | G10: Puma | H10: MER-A0-1801 | I10: 45320 | J10: =YEAR(Tabla1[[#This Row],[FECHA DE COMPRA]]) -> 2024 | K10: 144.35 | L10: 0.2 | M10: =Tienda!$K19-Tienda!$K19*Tienda!$L19 -> 24.232 | N10: Efectivo | O10: No | P10: 45320 | Q10: 0
A11: DEP-A0-3447 | B11: Femenino | C11: 32 | D11: =IF(Tabla1[[#This Row],[EDAD]]<=35,"Adultos jóvenes 18 - 35 años",IF(C11>=36,"Adultos mayores 36 años en adelante")) -> Adultos jóvenes 18 - 35 años | E11: Camisa | F11: Rojo | G11: Tommy | H11: MER-A0-3447 | I11: 45322 | J11: =YEAR(Tabla1[[#This Row],[FECHA DE COMPRA]]) -> 2024 | K11: 86.15 | L11: 0.1 | M11: =Tienda!$K20-Tienda!$K20*Tienda!$L20 -> 84.52 | N11: Efectivo | O11: No | P11: 45322 | Q11: 0
A12: DEP-A0-4440 | B12: Femenino | C12: 18 | D12: =IF(Tabla1[[#This Row],[EDAD]]<=35,"Adultos jóvenes 18 - 35 años",IF(C12>=36,"Adultos mayores 36 años en adelante")) -> Adultos jóvenes 18 - 35 años | E12: Chaqueta | F12: Negro | G12: Tommy | H12: MER-A0-4440 | I12: 45325 | J12: =YEAR(Tabla1[[#This Row],[FECHA DE COMPRA]]) -> 2024 | K12: 19.75 | L12: 0 | M12: =Tienda!$K22-Tienda!$K22*Tienda!$L22 -> 87.147 | N12: Efectivo | O12: No | P12: 45325 | Q12: 0
A13: DEP-A0-0153 | B13: Femenino | C13: 34 | D13: =IF(Tabla1[[#This Row],[EDAD]]<=35,"Adultos jóvenes 18 - 35 años",IF(C13>=36,"Adultos mayores 36 años en adelante")) -> Adultos jóvenes 18 - 35 años | E13: Falda | F13: Rojo | G13: Nike | H13: MER-A0-0153 | I13: 45325 | J13: =YEAR(Tabla1[[#This Row],[FECHA DE COMPRA]]) -> 2024 | K13: 62.52 | L13: 0.2 | M13: =Tienda!$K24-Tienda!$K24*Tienda!$L24 -> 37.87 | N13: Efectivo | O13: No | P13: 45325 | Q13: 0
A14: DEP-A0-4820 | B14: Masculino | C14: 18 | D14: =IF(Tabla1[[#This Row],[EDAD]]<=35,"Adultos jóvenes 18 - 35 años",IF(C14>=36,"Adultos mayores 36 años en adelante")) -> Adultos jóvenes 18 - 35 años | E14: Chaqueta | F14: Gris | G14: Zara | H14: MER-A0-4820 | I14: 45325 | J14: =YEAR(Tabla1[[#This Row],[FECHA DE COMPRA]]) -> 2024 | K14: 167.79 | L14: 0.2 | M14: =Tienda!$K25-Tienda!$K25*Tienda!$L25 -> 144.47 | N14: Efectivo | O14: No | P14: 45325 | Q14: 0
A15: DEP-A0-1547 | B15: Masculino | C15: 21 | D15: =IF(Tabla1[[#This Row],[EDAD]]<=35,"Adultos jóvenes 18 - 35 años",IF(C15>=36,"Adultos mayores 36 años en adelante")) -> Adultos jóvenes 18 - 35 años | E15: Zapatos | F15: Gris | G15: Levis | H15: MER-A0-1547 | I15: 45330 | J15: =YEAR(Tabla1[[#This Row],[FECHA DE COMPRA]]) -> 2024 | K15: 97.71 | L15: 0.1 | M15: =Tienda!$K30-Tienda!$K30*Tienda!$L30 -> 32.585 | N15: Efectivo | O15: No | P15: 45330 | Q15: 0
A16: DEP-A0-2742 | B16: Femenino | C16: 35 | D16: =IF(Tabla1[[#This Row],[EDAD]]<=35,"Adultos jóvenes 18 - 35 años",IF(C16>=36,"Adultos mayores 36 años en adelante")) -> Adultos jóvenes 18 - 35 años | E16: Pantalón | F16: Gris | G16: Nike | H16: MER-A0-2742 | I16: 45330 | J16: =YEAR(Tabla1[[#This Row],[FECHA DE COMPRA]]) -> 2024 | K16: 182.89 | L16: 0.3 | M16: =Tienda!$K32-Tienda!$K32*Tienda!$L32 -> 15.984 | N16: Efectivo | O16: No | P16: 45330 | Q16: 0
A17: DEP-A0-2624 | B17: Femenino | C17: 25 | D17: =IF(Tabla1[[#This Row],[EDAD]]<=35,"Adultos jóvenes 18 - 35 años",IF(C17>=36,"Adultos mayores 36 años en adelante")) -> Adultos jóvenes 18 - 35 años | E17: Falda | F17: Gris | G17: Zara | H17: MER-A0-2624 | I17: 45336 | J17: =YEAR(Tabla1[[#This Row],[FECHA DE COMPRA]]) -> 2024 | K17: 166.73 | L17: 0.2 | M17: =Tienda!$K38-Tienda!$K38*Tienda!$L38 -> 146.82 | N17: Efectivo | O17: No | P17: 45336 | Q17: 0
A18: DEP-A0-0966 | B18: Femenino | C18: 24 | D18: =IF(Tabla1[[#This Row],[EDAD]]<=35,"Adultos jóvenes 18 - 35 años",IF(C18>=36,"Adultos mayores 36 años en adelante")) -> Adultos jóvenes 18 - 35 años | E18: Vestido | F18: Rojo | G18: Zara | H18: MER-A0-0966 | I18: 45337 | J18: =YEAR(Tabla1[[#This Row],[FECHA DE COMPRA]]) -> 2024 | K18: 36.2 | L18: 0.2 | M18: =Tienda!$K40-Tienda!$K40*Tienda!$L40 -> 173.448 | N18: Efectivo | O18: No | P18: 45337 | Q18: 0
A19: DEP-A0-2461 | B19: Femenino | C19: 18 | D19: =IF(Tabla1[[#This Row],[EDAD]]<=35,"Adultos jóvenes 18 - 35 años",IF(C19>=36,"Adultos mayores 36 años en adelante")) -> Adultos jóvenes 18 - 35 años | E19: Zapatos | F19: Azul | G19: Adidas | H19: MER-A0-2461 | I19: 45342 | J19: =YEAR(Tabla1[[#This Row],[FECHA DE COMPRA]]) -> 2024 | K19: 30.29 | L19: 0.2 | M19: =Tienda!$K46-Tienda!$K46*Tienda!$L46 -> 60.011 | N19: Efectivo | O19: No | P19: 45342 | Q19: 0
A20: DEP-A0-3469 | B20: Femenino | C20: 20 | D20: =IF(Tabla1[[#This Row],[EDAD]]<=35,"Adultos jóvenes 18 - 35 años",IF(C20>=36,"Adultos mayores 36 años en adelante")) -> Adultos jóvenes 18 - 35 años | E20: Falda | F20: Verde | G20: Puma | H20: MER-A0-3469 | I20: 45342 | J20: =YEAR(Tabla1[[#This Row],[FECHA DE COMPRA]]) -> 2024 | K20: 105.65 | L20: 0.2 | M20: =Tienda!$K48-Tienda!$K48*Tienda!$L48 -> 157.73 | N20: Efectivo | O20: No | P20: 45342 | Q20: 0
A21: DEP-A0-3493 | B21: Femenino | C21: 26 | D21: =IF(Tabla1[[#This Row],[EDAD]]<=35,"Adultos jóvenes 18 - 35 años",IF(C21>=36,"Adultos mayores 36 años en adelante")) -> Adultos jóvenes 18 - 35 años | E21: Blusa | F21: Negro | G21: Tommy | H21: MER-A0-3493 | I21: 45344 | J21: =YEAR(Tabla1[[#This Row],[FECHA DE COMPRA]]) -> 2024 | K21: 74.15 | L21: 0 | M21: =Tienda!$K52-Tienda!$K52*Tienda!$L52 -> 45.68 | N21: Efectivo | O21: No | P21: 45344 | Q21: 0
A22: DEP-A0-0929 | B22: Femenino | C22: 22 | D22: =IF(Tabla1[[#This Row],[EDAD]]<=35,"Adultos jóvenes 18 - 35 años",IF(C22>=36,"Adultos mayores 36 años en adelante")) -> Adultos jóvenes 18 - 35 años | E22: Pantalón | F22: Azul | G22: Nike | H22: MER-A0-0929 | I22: 45344 | J22: =YEAR(Tabla1[[#This Row],[FECHA DE COMPRA]]) -> 2024 | K22: 96.83 | L22: 0.1 | M22: =Tienda!$K53-Tienda!$K53*Tienda!$L53 -> 105.4 | N22: Efectivo | O22: No | P22: 45344 | Q22: 0
A23: DEP-A0-3515 | B23: Femenino | C23: 24 | D23: =IF(Tabla1[[#This Row],[EDAD]]<=35,"Adultos jóvenes 18 - 35 años",IF(C23>=36,"Adultos mayores 36 años en adelante")) -> Adultos jóvenes 18 - 35 años | E23: Zapatos | F23: Azul | G23: Levis | H23: MER-A0-3515 | I23: 45344 | J23: =YEAR(Tabla1[[#This Row],[FECHA DE COMPRA]]) -> 2024 | K23: 190.13 | L23: 0.1 | M23: =Tienda!$K55-Tienda!$K55*Tienda!$L55 -> 89.019 | N23: Efectivo | O23: No | P23: 45344 | Q23: 0
A24: DEP-A0-3698 | B24: Femenino | C24: 24 | D24: =IF(Tabla1[[#This Row],[EDAD]]<=35,"Adultos jóvenes 18 - 35 años",IF(C24>=36,"Adultos mayores 36 años en adelante")) -> Adultos jóvenes 18 - 35 años | E24: Blusa | F24: Gris | G24: Zara | H24: MER-A0-3698 | I24: 45349 | J24: =YEAR(Tabla1[[#This Row],[FECHA DE COMPRA]]) -> 2024 | K24: 37.87 | L24: 0 | M24: =Tienda!$K61-Tienda!$K61*Tienda!$L61 -> 34.51 | N24: Efectivo | O24: No | P24: 45349 | Q24: 0
A25: DEP-A0-2456 | B25: Femenino | C25: 33 | D25: =IF(Tabla1[[#This Row],[EDAD]]<=35,"Adultos jóvenes 18 - 35 años",IF(C25>=36,"Adultos mayores 36 años en adelante")) -> Adultos jóvenes 18 - 35 años | E25: Blusa | F25: Azul | G25: Mango | H25: MER-A0-2456 | I25: 45335 | J25: =YEAR(Tabla1[[#This Row],[FECHA DE COMPRA]]) -> 2024 | K25: 144.47 | L25: 0 | M25: =Tienda!$K64-Tienda!$K64*Tienda!$L64 -> 138.456 | N25: Efectivo | O25: No | P25: 45371 | Q25: 0
A26: DEP-A0-3450 | B26: Femenino | C26: 34 | D26: =IF(Tabla1[[#This Row],[EDAD]]<=35,"Adultos jóvenes 18 - 35 años",IF(C26>=36,"Adultos mayores 36 años en adelante")) -> Adultos jóvenes 18 - 35 años | E26: Pantalón | F26: Azul | G26: Nike | H26: MER-A0-3450 | I26: 45335 | J26: =YEAR(Tabla1[[#This Row],[FECHA DE COMPRA]]) -> 2024 | K26: 106.54 | L26: 0.1 | M26: =Tienda!$K65-Tienda!$K65*Tienda!$L65 -> 7.056 | N26: Efectivo | O26: No | P26: 45373 | Q26: 0
A27: DEP-A0-0441 | B27: Femenino | C27: 22 | D27: =IF(Tabla1[[#This Row],[EDAD]]<=35,"Adultos jóvenes 18 - 35 años",IF(C27>=36,"Adultos mayores 36 años en adelante")) -> Adultos jóvenes 18 - 35 años | E27: Camisa | F27: Blanco | G27: Puma | H27: MER-A0-0441 | I27: 45335 | J27: =YEAR(Tabla1[[#This Row],[FECHA DE COMPRA]]) -> 2024 | K27: 128.9 | L27: 0.3 | M27: =Tienda!$K66-Tienda!$K66*Tienda!$L66 -> 56.105 | N27: Efectivo | O27: No | P27: 45373 | Q27: 0
A28: DEP-A0-0079 | B28: Femenino | C28: 21 | D28: =IF(Tabla1[[#This Row],[EDAD]]<=35,"Adultos jóvenes 18 - 35 años",IF(C28>=36,"Adultos mayores 36 años en adelante")) -> Adultos jóvenes 18 - 35 años | E28: Blusa | F28: Gris | G28: Levis | H28: MER-A0-0079 | I28: 45335 | J28: =YEAR(Tabla1[[#This Row],[FECHA DE COMPRA]]) -> 2024 | K28: 177.21 | L28: 0 | M28: =Tienda!$K67-Tienda!$K67*Tienda!$L67 -> 165.46 | N28: Efectivo | O28: No | P28: 45375 | Q28: 0
A29: DEP-A0-1068 | B29: Masculino | C29: 30 | D29: =IF(Tabla1[[#This Row],[EDAD]]<=35,"Adultos jóvenes 18 - 35 años",IF(C29>=36,"Adultos mayores 36 años en adelante")) -> Adultos jóvenes 18 - 35 años | E29: Chaqueta | F29: Verde | G29: Mango | H29: MER-A0-1068 | I29: 45352 | J29: =YEAR(Tabla1[[#This Row],[FECHA DE COMPRA]]) -> 2024 | K29: 91.63 | L29: 0.1 | M29: =Tienda!$K70-Tienda!$K70*Tienda!$L70 -> 86.4 | N29: Efectivo | O29: No | P29: 45352 | Q29: 0
A30: DEP-A0-0112 | B30: Masculino | C30: 22 | D30: =IF(Tabla1[[#This Row],[EDAD]]<=35,"Adultos jóvenes 18 - 35 años",IF(C30>=36,"Adultos mayores 36 años en adelante")) -> Adultos jóvenes 18 - 35 años | E30: Zapatos | F30: Verde | G30: Levis | H30: MER-A0-0112 | I30: 45354 | J30: =YEAR(Tabla1[[#This Row],[FECHA DE COMPRA]]) -> 2024 | K30: 46.55 | L30: 0.3 | M30: =Tienda!$K72-Tienda!$K72*Tienda!$L72 -> 82.296 | N30: Efectivo | O30: No | P30: 45354 | Q30: 0
A31: DEP-A0-2097 | B31: Femenino | C31: 29 | D31: =IF(Tabla1[[#This Row],[EDAD]]<=35,"Adultos jóvenes 18 - 35 años",IF(C31>=36,"Adultos mayores 36 años en adelante")) -> Adultos jóvenes 18 - 35 años | E31: Vestido | F31: Rojo | G31: Mango | H31: MER-A0-2097 | I31: 45354 | J31: =YEAR(Tabla1[[#This Row],[FECHA DE COMPRA]]) -> 2024 | K31: 66.63 | L31: 0.2 | M31: =Tienda!$K73-Tienda!$K73*Tienda!$L73 -> 88.634 | N31: Efectivo | O31: No | P31: 45354 | Q31: 0
A32: DEP-A0-1776 | B32: Femenino | C32: 26 | D32: =IF(Tabla1[[#This Row],[EDAD]]<=35,"Adultos jóvenes 18 - 35 años",IF(C32>=36,"Adultos mayores 36 años en adelante")) -> Adultos jóvenes 18 - 35 años | E32: Chaqueta | F32: Negro | G32: Tommy | H32: MER-A0-1776 | I32: 45356 | J32: =YEAR(Tabla1[[#This Row],[FECHA DE COMPRA]]) -> 2024 | K32: 19.98 | L32: 0.2 | M32: =Tienda!$K76-Tienda!$K76*Tienda!$L76 -> 31.297 | N32: Efectivo | O32: No | P32: 45356 | Q32: 0
A33: DEP-A0-3152 | B33: Masculino | C33: 29 | D33: =IF(Tabla1[[#This Row],[EDAD]]<=35,"Adultos jóvenes 18 - 35 años",IF(C33>=36,"Adultos mayores 36 años en adelante")) -> Adultos jóvenes 18 - 35 años | E33: Chaqueta | F33: Rojo | G33: Tommy | H33: MER-A0-3152 | I33: 45356 | J33: =YEAR(Tabla1[[#This Row],[FECHA DE COMPRA]]) -> 2024 | K33: 140.78 | L33: 0.3 | M33: =Tienda!$K78-Tienda!$K78*Tienda!$L78 -> 47.7 | N33: Efectivo | O33: No | P33: 45356 | Q33: 0
A34: DEP-A0-4394 | B34: Femenino | C34: 25 | D34: =IF(Tabla1[[#This Row],[EDAD]]<=35,"Adultos jóvenes 18 - 35 años",IF(C34>=36,"Adultos mayores 36 años en adelante")) -> Adultos jóvenes 18 - 35 años | E34: Blusa | F34: Blanco | G34: Zara | H34: MER-A0-4394 | I34: 45361 | J34: =YEAR(Tabla1[[#This Row],[FECHA DE COMPRA]]) -> 2024 | K34: 111.82 | L34: 0.2 | M34: =Tienda!$K84-Tienda!$K84*Tienda!$L84 -> 180.76 | N34: Efectivo | O34: No | P34: 45361 | Q34: 0
A35: DEP-A0-1317 | B35: Femenino | C35: 18 | D35: =IF(Tabla1[[#This Row],[EDAD]]<=35,"Adultos jóvenes 18 - 35 años",IF(C35>=36,"Adultos mayores 36 años en adelante")) -> Adultos jóvenes 18 - 35 años | E35: Vestido | F35: Negro | G35: Zara | H35: MER-A0-1317 | I35: 45361 | J35: =YEAR(Tabla1[[#This Row],[FECHA DE COMPRA]]) -> 2024 | K35: 153.58 | L35: 0.2 | M35: =Tienda!$K85-Tienda!$K85*Tienda!$L85 -> 94.635 | N35: Efectivo | O35: No | P35: 45361 | Q35: 0
A36: DEP-A0-0785 | B36: Femenino | C36: 29 | D36: =IF(Tabla1[[#This Row],[EDAD]]<=35,"Adultos jóvenes 18 - 35 años",IF(C36>=36,"Adultos mayores 36 años en adelante")) -> Adultos jóvenes 18 - 35 años | E36: Blusa | F36: Verde | G36: Zara | H36: MER-A0-0785 | I36: 45362 | J36: =YEAR(Tabla1[[#This Row],[FECHA DE COMPRA]]) -> 2024 | K36: 38.58 | L36: 0.1 | M36: =Tienda!$K86-Tienda!$K86*Tienda!$L86 -> 135.24 | N36: Efectivo | O36: No | P36: 45362 | Q36: 0
A37: DEP-A0-3475 | B37: Femenino | C37: 21 | D37: =IF(Tabla1[[#This Row],[EDAD]]<=35,"Adultos jóvenes 18 - 35 años",IF(C37>=36,"Adultos mayores 36 años en adelante")) -> Adultos jóvenes 18 - 35 años | E37: Zapatos | F37: Negro | G37: Zara | H37: MER-A0-3475 | I37: 45364 | J37: =YEAR(Tabla1[[#This Row],[FECHA DE COMPRA]]) -> 2024 | K37: 134.2 | L37: 0.3 | M37: =Tienda!$K87-Tienda!$K87*Tienda!$L87 -> 66.28 | N37: Efectivo | O37: No | P37: 45364 | Q37: 0
A38: DEP-A0-4443 | B38: Masculino | C38: 20 | D38: =IF(Tabla1[[#This Row],[EDAD]]<=35,"Adultos jóvenes 18 - 35 años",IF(C38>=36,"Adultos mayores 36 años en adelante")) -> Adultos jóvenes 18 - 35 años | E38: Chaqueta | F38: Rojo | G38: Zara | H38: MER-A0-4443 | I38: 45365 | J38: =YEAR(Tabla1[[#This Row],[FECHA DE COMPRA]]) -> 2024 | K38: 146.82 | L38: 0 | M38: =Tienda!$K93-Tienda!$K93*Tienda!$L93 -> 78.96 | N38: Efectivo | O38: No | P38: 45365 | Q38: 0
A39: DEP-A0-0232 | B39: Masculino | C39: 19 | D39: =IF(Tabla1[[#This Row],[EDAD]]<=35,"Adultos jóvenes 18 - 35 años",IF(C39>=36,"Adultos mayores 36 años en adelante")) -> Adultos jóvenes 18 - 35 años | E39: Chaqueta | F39: Amarillo | G39: Zara | H39: MER-A0-0232 | I39: 45365 | J39: =YEAR(Tabla1[[#This Row],[FECHA DE COMPRA]]) -> 2024 | K39: 198.04 | L39: 0.1 | M39: =Tienda!$K94-Tienda!$K94*Tienda!$L94 -> 119.511 | N39: Efectivo | O39: No | P39: 45365 | Q39: 0
A40: DEP-A0-3173 | B40: Femenino | C40: 35 | D40: =IF(Tabla1[[#This Row],[EDAD]]<=35,"Adultos jóvenes 18 - 35 años",IF(C40>=36,"Adultos mayores 36 años en adelante")) -> Adultos jóvenes 18 - 35 años | E40: Blusa | F40: Negro | G40: Levis | H40: MER-A0-3173 | I40: 45375 | J40: =YEAR(Tabla1[[#This Row],[FECHA DE COMPRA]]) -> 2024 | K40: 192.72 | L40: 0.1 | M40: =Tienda!$K96-Tienda!$K96*Tienda!$L96 -> 84.942 | N40: Efectivo | O40: No | P40: 45375 | Q40: 0
A41: DEP-A0-0955 | B41: Masculino | C41: 34 | D41: =IF(Tabla1[[#This Row],[EDAD]]<=35,"Adultos jóvenes 18 - 35 años",IF(C41>=36,"Adultos mayores 36 años en adelante")) -> Adultos jóvenes 18 - 35 años | E41: Camisa | F41: Rojo | G41: Mango | H41: MER-A0-0955 | I41: 45376 | J41: =YEAR(Tabla1[[#This Row],[FECHA DE COMPRA]]) -> 2024 | K41: 20.52 | L41: 0.1 | M41: =Tienda!$K97-Tienda!$K97*Tienda!$L97 -> 102.84 | N41: Efectivo | O41: No | P41: 45376 | Q41: 0
A42: DEP-A0-2584 | B42: Femenino | C42: 20 | D42: =IF(Tabla1[[#This Row],[EDAD]]<=35,"Adultos jóvenes 18 - 35 años",IF(C42>=36,"Adultos mayores 36 años en adelante")) -> Adultos jóvenes 18 - 35 años | E42: Vestido | F42: Blanco | G42: Nike | H42: MER-A0-2584 | I42: 45376 | J42: =YEAR(Tabla1[[#This Row],[FECHA DE COMPRA]]) -> 2024 | K42: 170.4 | L42: 0.2 | M42: =Tienda!$K98-Tienda!$K98*Tienda!$L98 -> 26.304 | N42: Efectivo | O42: No | P42: 45376 | Q42: 0
A43: DEP-A0-1093 | B43: Femenino | C43: 31 | D43: =IF(Tabla1[[#This Row],[EDAD]]<=35,"Adultos jóvenes 18 - 35 años",IF(C43>=36,"Adultos mayores 36 años en adelante")) -> Adultos jóvenes 18 - 35 años | E43: Falda | F43: Negro | G43: Adidas | H43: MER-A0-1093 | I43: 45382 | J43: =YEAR(Tabla1[[#This Row],[FECHA DE COMPRA]]) -> 2024 | K43: 128.41 | L43: 0.3 | M43: =Tienda!$K105-Tienda!$K105*Tienda!$L105 -> 47.999 | N43: Efectivo | O43: No | P43: 45382 | Q43: 0
A44: DEP-A0-1826 | B44: Femenino | C44: 33 | D44: =IF(Tabla1[[#This Row],[EDAD]]<=35,"Adultos jóvenes 18 - 35 años",IF(C44>=36,"Adultos mayores 36 años en adelante")) -> Adultos jóvenes 18 - 35 años | E44: Blusa | F44: Gris | G44: Adidas | H44: MER-A0-1826 | I44: 45382 | J44: =YEAR(Tabla1[[#This Row],[FECHA DE COMPRA]]) -> 2024 | K44: 187.7 | L44: 0.2 | M44: =Tienda!$K108-Tienda!$K108*Tienda!$L108 -> 120.06 | N44: Efectivo | O44: No | P44: 45382 | Q44: 0
A45: DEP-A0-4776 | B45: Femenino | C45: 27 | D45: =IF(Tabla1[[#This Row],[EDAD]]<=35,"Adultos jóvenes 18 - 35 años",IF(C45>=36,"Adultos mayores 36 años en adelante")) -> Adultos jóvenes 18 - 35 años | E45: Zapatos | F45: Gris | G45: Zara | H45: MER-A0-4776 | I45: 45383 | J45: =YEAR(Tabla1[[#This Row],[FECHA DE COMPRA]]) -> 2024 | K45: 72.7 | L45: 0 | M45: =Tienda!$K109-Tienda!$K109*Tienda!$L109 -> 92.84 | N45: Efectivo | O45: No | P45: 45383 | Q45: 0
A46: DEP-A0-2011 | B46: Masculino | C46: 33 | D46: =IF(Tabla1[[#This Row],[EDAD]]<=35,"Adultos jóvenes 18 - 35 años",IF(C46>=36,"Adultos mayores 36 años en adelante")) -> Adultos jóvenes 18 - 35 años | E46: Zapatos | F46: Verde | G46: Levis | H46: MER-A0-2011 | I46: 45384 | J46: =YEAR(Tabla1[[#This Row],[FECHA DE COMPRA]]) -> 2024 | K46: 85.73 | L46: 0.3 | M46: =Tienda!$K113-Tienda!$K113*Tienda!$L113 -> 157.37 | N46: Efectivo | O46: No | P46: 45384 | Q46: 0
A47: DEP-A0-2317 | B47: Femenino | C47: 21 | D47: =IF(Tabla1[[#This Row],[EDAD]]<=35,"Adultos jóvenes 18 - 35 años",IF(C47>=36,"Adultos mayores 36 años en adelante")) -> Adultos jóvenes 18 - 35 años | E47: Blusa | F47: Gris | G47: Adidas | H47: MER-A0-2317 | I47: 45385 | J47: =YEAR(Tabla1[[#This Row],[FECHA DE COMPRA]]) -> 2024 | K47: 108.43 | L47: 0.1 | M47: =Tienda!$K117-Tienda!$K117*Tienda!$L117 -> 138.593 | N47: Efectivo | O47: No | P47: 45385 | Q47: 0
A48: DEP-A0-2986 | B48: Femenino | C48: 18 | D48: =IF(Tabla1[[#This Row],[EDAD]]<=35,"Adultos jóvenes 18 - 35 años",IF(C48>=36,"Adultos mayores 36 años en adelante")) -> Adultos jóvenes 18 - 35 años | E48: Vestido | F48: Azul | G48: Tommy | H48: MER-A0-2986 | I48: 45388 | J48: =YEAR(Tabla1[[#This Row],[FECHA DE COMPRA]]) -> 2024 | K48: 157.73 | L48: 0 | M48: =Tienda!$K122-Tienda!$K122*Tienda!$L122 -> 111.51 | N48: Efectivo | O48: No | P48: 45388 | Q48: 0
A49: DEP-A0-4738 | B49: Masculino | C49: 29 | D49: =IF(Tabla1[[#This Row],[EDAD]]<=35,"Adultos jóvenes 18 - 35 años",IF(C49>=36,"Adultos mayores 36 años en adelante")) -> Adultos jóvenes 18 - 35 años | E49: Chaqueta | F49: Verde | G49: Puma | H49: MER-A0-4738 | I49: 45390 | J49: =YEAR(Tabla1[[#This Row],[FECHA DE COMPRA]]) -> 2024 | K49: 51.76 | L49: 0.2 | M49: =Tienda!$K124-Tienda!$K124*Tienda!$L124 -> 135.49 | N49: Efectivo | O49: No | P49: 45390 | Q49: 0
A50: DEP-A0-4981 | B50: Femenino | C50: 31 | D50: =IF(Tabla1[[#This Row],[EDAD]]<=35,"Adultos jóvenes 18 - 35 años",IF(C50>=36,"Adultos mayores 36 años en adelante")) -> Adultos jóvenes 18 - 35 años | E50: Pantalón | F50: Amarillo | G50: Tommy | H50: MER-A0-4981 | I50: 45391 | J50: =YEAR(Tabla1[[#This Row],[FECHA DE COMPRA]]) -> 2024 | K50: 23.35 | L50: 0.3 | M50: =Tienda!$K128-Tienda!$K128*Tienda!$L128 -> 102.65 | N50: Efectivo | O50: No | P50: 45391 | Q50: 0
A51: DEP-A0-4814 | B51: Femenino | C51: 31 | D51: =IF(Tabla1[[#This Row],[EDAD]]<=35,"Adultos jóvenes 18 - 35 años",IF(C51>=36,"Adultos mayores 36 años en adelante")) -> Adultos jóvenes 18 - 35 años | E51: Pantalón | F51: Gris | G51: Nike | H51: MER-A0-4814 | I51: 45398 | J51: =YEAR(Tabla1[[#This Row],[FECHA DE COMPRA]]) -> 2024 | K51: 103.3 | L51: 0.3 | M51: =Tienda!$K129-Tienda!$K129*Tienda!$L129 -> 115.997 | N51: Efectivo | O51: No | P51: 45398 | Q51: 0
A52: DEP-A0-1013 | B52: Femenino | C52: 28 | D52: =IF(Tabla1[[#This Row],[EDAD]]<=35,"Adultos jóvenes 18 - 35 años",IF(C52>=36,"Adultos mayores 36 años en adelante")) -> Adultos jóvenes 18 - 35 años | E52: Zapatos | F52: Verde | G52: Adidas | H52: MER-A0-1013 | I52: 45399 | J52: =YEAR(Tabla1[[#This Row],[FECHA DE COMPRA]]) -> 2024 | K52: 57.1 | L52: 0.2 | M52: =Tienda!$K130-Tienda!$K130*Tienda!$L130 -> 174.42 | N52: Efectivo | O52: No | P52: 45399 | Q52: 0
A53: DEP-A0-4953 | B53: Femenino | C53: 30 | D53: =IF(Tabla1[[#This Row],[EDAD]]<=35,"Adultos jóvenes 18 - 35 años",IF(C53>=36,"Adultos mayores 36 años en adelante")) -> Adultos jóvenes 18 - 35 años | E53: Zapatos | F53: Amarillo | G53: Mango | H53: MER-A0-4953 | I53: 45399 | J53: =YEAR(Tabla1[[#This Row],[FECHA DE COMPRA]]) -> 2024 | K53: 105.4 | L53: 0 | M53: =Tienda!$K132-Tienda!$K132*Tienda!$L132 -> 79.394 | N53: Efectivo | O53: No | P53: 45399 | Q53: 0
A54: DEP-A0-4492 | B54: Masculino | C54: 29 | D54: =IF(Tabla1[[#This Row],[EDAD]]<=35,"Adultos jóvenes 18 - 35 años",IF(C54>=36,"Adultos mayores 36 años en adelante")) -> Adultos jóvenes 18 - 35 años | E54: Camisa | F54: Verde | G54: Tommy | H54: MER-A0-4492 | I54: 45399 | J54: =YEAR(Tabla1[[#This Row],[FECHA DE COMPRA]]) -> 2024 | K54: 198.26 | L54: 0.3 | M54: =Tienda!$K134-Tienda!$K134*Tienda!$L134 -> 11.736 | N54: Efectivo | O54: No | P54: 45399 | Q54: 0
A55: DEP-A0-4145 | B55: Masculino | C55: 18 | D55: =IF(Tabla1[[#This Row],[EDAD]]<=35,"Adultos jóvenes 18 - 35 años",IF(C55>=36,"Adultos mayores 36 años en adelante")) -> Adultos jóvenes 18 - 35 años | E55: Chaqueta | F55: Amarillo | G55: Adidas | H55: MER-A0-4145 | I55: 45401 | J55: =YEAR(Tabla1[[#This Row],[FECHA DE COMPRA]]) -> 2024 | K55: 98.91 | L55: 0.1 | M55: =Tienda!$K139-Tienda!$K139*Tienda!$L139 -> 138.726 | N55: Efectivo | O55: No | P55: 45401 | Q55: 0
A56: DEP-A0-4170 | B56: Femenino | C56: 23 | D56: =IF(Tabla1[[#This Row],[EDAD]]<=35,"Adultos jóvenes 18 - 35 años",IF(C56>=36,"Adultos mayores 36 años en adelante")) -> Adultos jóvenes 18 - 35 años | E56: Zapatos | F56: Gris | G56: Levis | H56: MER-A0-4170 | I56: 45401 | J56: =YEAR(Tabla1[[#This Row],[FECHA DE COMPRA]]) -> 2024 | K56: 100.41 | L56: 0.1 | M56: =Tienda!$K140-Tienda!$K140*Tienda!$L140 -> 43.256 | N56: Efectivo | O56: No | P56: 45401 | Q56: 0
A57: DEP-A0-1507 | B57: Masculino | C57: 19 | D57: =IF(Tabla1[[#This Row],[EDAD]]<=35,"Adultos jóvenes 18 - 35 años",IF(C57>=36,"Adultos mayores 36 años en adelante")) -> Adultos jóvenes 18 - 35 años | E57: Chaqueta | F57: Azul | G57: Adidas | H57: MER-A0-1507 | I57: 45406 | J57: =YEAR(Tabla1[[#This Row],[FECHA DE COMPRA]]) -> 2024 | K57: 121.04 | L57: 0 | M57: =Tienda!$K142-Tienda!$K142*Tienda!$L142 -> 153.963 | N57: Efectivo | O57: No | P57: 45406 | Q57: 0
A58: DEP-A0-4878 | B58: Femenino | C58: 21 | D58: =IF(Tabla1[[#This Row],[EDAD]]<=35,"Adultos jóvenes 18 - 35 años",IF(C58>=36,"Adultos mayores 36 años en adelante")) -> Adultos jóvenes 18 - 35 años | E58: Falda | F58: Azul | G58: Levis | H58: MER-A0-4878 | I58: 45406 | J58: =YEAR(Tabla1[[#This Row],[FECHA DE COMPRA]]) -> 2024 | K58: 124.36 | L58: 0.3 | M58: =Tienda!$K143-Tienda!$K143*Tienda!$L143 -> 147.43 | N58: Efectivo | O58: No | P58: 45406 | Q58: 0
A59: DEP-A0-2849 | B59: Masculino | C59: 24 | D59: =IF(Tabla1[[#This Row],[EDAD]]<=35,"Adultos jóvenes 18 - 35 años",IF(C59>=36,"Adultos mayores 36 años en adelante")) -> Adultos jóvenes 18 - 35 años | E59: Pantalón | F59: Azul | G59: Puma | H59: MER-A0-2849 | I59: 45406 | J59: =YEAR(Tabla1[[#This Row],[FECHA DE COMPRA]]) -> 2024 | K59: 143.26 | L59: 0.2 | M59: =Tienda!$K144-Tienda!$K144*Tienda!$L144 -> 76.912 | N59: Efectivo | O59: No | P59: 45406 | Q59: 0
A60: DEP-A0-3094 | B60: Femenino | C60: 24 | D60: =IF(Tabla1[[#This Row],[EDAD]]<=35,"Adultos jóvenes 18 - 35 años",IF(C60>=36,"Adultos mayores 36 años en adelante")) -> Adultos jóvenes 18 - 35 años | E60: Falda | F60: Rojo | G60: Puma | H60: MER-A0-3094 | I60: 45407 | J60: =YEAR(Tabla1[[#This Row],[FECHA DE COMPRA]]) -> 2024 | K60: 77.95 | L60: 0.1 | M60: =Tienda!$K146-Tienda!$K146*Tienda!$L146 -> 62.916 | N60: Efectivo | O60: No | P60: 45407 | Q60: 0
A61: DEP-A0-1832 | B61: Femenino | C61: 23 | D61: =IF(Tabla1[[#This Row],[EDAD]]<=35,"Adultos jóvenes 18 - 35 años",IF(C61>=36,"Adultos mayores 36 años en adelante")) -> Adultos jóvenes 18 - 35 años | E61: Falda | F61: Blanco | G61: Zara | H61: MER-A0-1832 | I61: 45414 | J61: =YEAR(Tabla1[[#This Row],[FECHA DE COMPRA]]) -> 2024 | K61: 49.3 | L61: 0.3 | M61: =Tienda!$K155-Tienda!$K155*Tienda!$L155 -> 137.718 | N61: Efectivo | O61: No | P61: 45414 | Q61: 0
A62: DEP-A0-1775 | B62: Femenino | C62: 22 | D62: =IF(Tabla1[[#This Row],[EDAD]]<=35,"Adultos jóvenes 18 - 35 años",IF(C62>=36,"Adultos mayores 36 años en adelante")) -> Adultos jóvenes 18 - 35 años | E62: Falda | F62: Amarillo | G62: Levis | H62: MER-A0-1775 | I62: 45414 | J62: =YEAR(Tabla1[[#This Row],[FECHA DE COMPRA]]) -> 2024 | K62: 137.65 | L62: 0.2 | M62: =Tienda!$K159-Tienda!$K159*Tienda!$L159 -> 17.647 | N62: Efectivo | O62: No | P62: 45414 | Q62: 0
A63: DEP-A0-3466 | B63: Femenino | C63: 32 | D63: =IF(Tabla1[[#This Row],[EDAD]]<=35,"Adultos jóvenes 18 - 35 años",IF(C63>=36,"Adultos mayores 36 años en adelante")) -> Adultos jóvenes 18 - 35 años | E63: Vestido | F63: Verde | G63: Nike | H63: MER-A0-3466 | I63: 45414 | J63: =YEAR(Tabla1[[#This Row],[FECHA DE COMPRA]]) -> 2024 | K63: 171.75 | L63: 0.3 | M63: =Tienda!$K160-Tienda!$K160*Tienda!$L160 -> 101.71 | N63: Efectivo | O63: No | P63: 45414 | Q63: 0
A64: DEP-A0-1437 | B64: Masculino | C64: 30 | D64: =IF(Tabla1[[#This Row],[EDAD]]<=35,"Adultos jóvenes 18 - 35 años",IF(C64>=36,"Adultos mayores 36 años en adelante")) -> Adultos jóvenes 18 - 35 años | E64: Zapatos | F64: Negro | G64: Puma | H64: MER-A0-1437 | I64: 45416 | J64: =YEAR(Tabla1[[#This Row],[FECHA DE COMPRA]]) -> 2024 | K64: 173.07 | L64: 0.2 | M64: =Tienda!$K167-Tienda!$K167*Tienda!$L167 -> 144.19 | N64: Efectivo | O64: No | P64: 45416 | Q64: 0
A65: DEP-A0-3568 | B65: Femenino | C65: 28 | D65: =IF(Tabla1[[#This Row],[EDAD]]<=35,"Adultos jóvenes 18 - 35 años",IF(C65>=36,"Adultos mayores 36 años en adelante")) -> Adultos jóvenes 18 - 35 años | E65: Chaqueta | F65: Rojo | G65: Mango | H65: MER-A0-3568 | I65: 45417 | J65: =YEAR(Tabla1[[#This Row],[FECHA DE COMPRA]]) -> 2024 | K65: 10.08 | L65: 0.3 | M65: =Tienda!$K169-Tienda!$K169*Tienda!$L169 -> 10.374 | N65: Efectivo | O65: No | P65: 45417 | Q65: 0
A66: DEP-A0-1543 | B66: Femenino | C66: 31 | D66: =IF(Tabla1[[#This Row],[EDAD]]<=35,"Adultos jóvenes 18 - 35 años",IF(C66>=36,"Adultos mayores 36 años en adelante")) -> Adultos jóvenes 18 - 35 años | E66: Blusa | F66: Amarillo | G66: Adidas | H66: MER-A0-1543 | I66: 45418 | J66: =YEAR(Tabla1[[#This Row],[FECHA DE COMPRA]]) -> 2024 | K66: 80.15 | L66: 0.3 | M66: =Tienda!$K173-Tienda!$K173*Tienda!$L173 -> 79.29 | N66: Efectivo | O66: No | P66: 45418 | Q66: 0
A67: DEP-A0-1682 | B67: Femenino | C67: 35 | D67: =IF(Tabla1[[#This Row],[EDAD]]<=35,"Adultos jóvenes 18 - 35 años",IF(C67>=36,"Adultos mayores 36 años en adelante")) -> Adultos jóvenes 18 - 35 años | E67: Zapatos | F67: Gris | G67: Nike | H67: MER-A0-1682 | I67: 45418 | J67: =YEAR(Tabla1[[#This Row],[FECHA DE COMPRA]]) -> 2024 | K67: 165.46 | L67: 0 | M67: =Tienda!$K176-Tienda!$K176*Tienda!$L176 -> 21.128 | N67: Efectivo | O67: No | P67: 45418 | Q67: 0
A68: DEP-A0-4015 | B68: Femenino | C68: 31 | D68: =IF(Tabla1[[#This Row],[EDAD]]<=35,"Adultos jóvenes 18 - 35 años",IF(C68>=36,"Adultos mayores 36 años en adelante")) -> Adultos jóvenes 18 - 35 años | E68: Vestido | F68: Azul | G68: Puma | H68: MER-A0-4015 | I68: 45418 | J68: =YEAR(Tabla1[[#This Row],[FECHA DE COMPRA]]) -> 2024 | K68: 166.17 | L68: 0 | M68: =Tienda!$K177-Tienda!$K177*Tienda!$L177 -> 119.03 | N68: Efectivo | O68: No | P68: 45418 | Q68: 0
A69: DEP-A0-0019 | B69: Masculino | C69: 23 | D69: =IF(Tabla1[[#This Row],[EDAD]]<=35,"Adultos jóvenes 18 - 35 años",IF(C69>=36,"Adultos mayores 36 años en adelante")) -> Adultos jóvenes 18 - 35 años | E69: Camisa | F69: Verde | G69: Levis | H69: MER-A0-0019 | I69: 45419 | J69: =YEAR(Tabla1[[#This Row],[FECHA DE COMPRA]]) -> 2024 | K69: 60.89 | L69: 0.1 | M69: =Tienda!$K179-Tienda!$K179*Tienda!$L179 -> 18.431 | N69: Efectivo | O69: No | P69: 45419 | Q69: 0
A70: DEP-A0-2582 | B70: Femenino | C70: 32 | D70: =IF(Tabla1[[#This Row],[EDAD]]<=35,"Adultos jóvenes 18 - 35 años",IF(C70>=36,"Adultos mayores 36 años en adelante")) -> Adultos jóvenes 18 - 35 años | E70: Falda | F70: Blanco | G70: Tommy | H70: MER-A0-2582 | I70: 45419 | J70: =YEAR(Tabla1[[#This Row],[FECHA DE COMPRA]]) -> 2024 | K70: 96 | L70: 0.1 | M70: =Tienda!$K180-Tienda!$K180*Tienda!$L180 -> 192.15 | N70: Efectivo | O70: No | P70: 45419 | Q70: 0
A71: DEP-A0-2297 | B71: Femenino | C71: 33 | D71: =IF(Tabla1[[#This Row],[EDAD]]<=35,"Adultos jóvenes 18 - 35 años",IF(C71>=36,"Adultos mayores 36 años en adelante")) -> Adultos jóvenes 18 - 35 años | E71: Blusa | F71: Verde | G71: Adidas | H71: MER-A0-2297 | I71: 45420 | J71: =YEAR(Tabla1[[#This Row],[FECHA DE COMPRA]]) -> 2024 | K71: 13.7 | L71: 0.2 | M71: =Tienda!$K182-Tienda!$K182*Tienda!$L182 -> 38.16 | N71: Efectivo | O71: No | P71: 45420 | Q71: 0
A72: DEP-A0-1056 | B72: Femenino | C72: 32 | D72: =IF(Tabla1[[#This Row],[EDAD]]<=35,"Adultos jóvenes 18 - 35 años",IF(C72>=36,"Adultos mayores 36 años en adelante")) -> Adultos jóvenes 18 - 35 años | E72: Falda | F72: Verde | G72: Tommy | H72: MER-A0-1056 | I72: 45420 | J72: =YEAR(Tabla1[[#This Row],[FECHA DE COMPRA]]) -> 2024 | K72: 91.44 | L72: 0.1 | M72: =Tienda!$K183-Tienda!$K183*Tienda!$L183 -> 54.392 | N72: Efectivo | O72: No | P72: 45420 | Q72: 0
A73: DEP-A0-4242 | B73: Femenino | C73: 33 | D73: =IF(Tabla1[[#This Row],[EDAD]]<=35,"Adultos jóvenes 18 - 35 años",IF(C73>=36,"Adultos mayores 36 años en adelante")) -> Adultos jóvenes 18 - 35 años | E73: Vestido | F73: Azul | G73: Tommy | H73: MER-A0-4242 | I73: 45425 | J73: =YEAR(Tabla1[[#This Row],[FECHA DE COMPRA]]) -> 2024 | K73: 126.62 | L73: 0.3 | M73: =Tienda!$K199-Tienda!$K199*Tienda!$L199 -> 40.467 | N73: Efectivo | O73: No | P73: 45425 | Q73: 0
A74: DEP-A0-4796 | B74: Masculino | C74: 32 | D74: =IF(Tabla1[[#This Row],[EDAD]]<=35,"Adultos jóvenes 18 - 35 años",IF(C74>=36,"Adultos mayores 36 años en adelante")) -> Adultos jóvenes 18 - 35 años | E74: Pantalón | F74: Verde | G74: Mango | H74: MER-A0-4796 | I74: 45425 | J74: =YEAR(Tabla1[[#This Row],[FECHA DE COMPRA]]) -> 2024 | K74: 126.75 | L74: 0 | M74: =Tienda!$K200-Tienda!$K200*Tienda!$L200 -> 11.872 | N74: Efectivo | O74: No | P74: 45425 | Q74: 0
A75: DEP-A0-4678 | B75: Femenino | C75: 33 | D75: =IF(Tabla1[[#This Row],[EDAD]]<=35,"Adultos jóvenes 18 - 35 años",IF(C75>=36,"Adultos mayores 36 años en adelante")) -> Adultos jóvenes 18 - 35 años | E75: Falda | F75: Gris | G75: Puma | H75: MER-A0-4678 | I75: 45425 | J75: =YEAR(Tabla1[[#This Row],[FECHA DE COMPRA]]) -> 2024 | K75: 131.27 | L75: 0.2 | M75: =Tienda!$K201-Tienda!$K201*Tienda!$L201 -> 113.408 | N75: Efectivo | O75: No | P75: 45425 | Q75: 0
A76: DEP-A0-0200 | B76: Femenino | C76: 25 | D76: =IF(Tabla1[[#This Row],[EDAD]]<=35,"Adultos jóvenes 18 - 35 años",IF(C76>=36,"Adultos mayores 36 años en adelante")) -> Adultos jóvenes 18 - 35 años | E76: Blusa | F76: Gris | G76: Zara | H76: MER-A0-0200 | I76: 45427 | J76: =YEAR(Tabla1[[#This Row],[FECHA DE COMPRA]]) -> 2024 | K76: 44.71 | L76: 0.3 | M76: =Tienda!$K206-Tienda!$K206*Tienda!$L206 -> 108.464 | N76: Efectivo | O76: No | P76: 45427 | Q76: 0
A77: DEP-A0-0367 | B77: Femenino | C77: 22 | D77: =IF(Tabla1[[#This Row],[EDAD]]<=35,"Adultos jóvenes 18 - 35 años",IF(C77>=36,"Adultos mayores 36 años en adelante")) -> Adultos jóvenes 18 - 35 años | E77: Vestido | F77: Verde | G77: Zara | H77: MER-A0-0367 | I77: 45427 | J77: =YEAR(Tabla1[[#This Row],[FECHA DE COMPRA]]) -> 2024 | K77: 73.35 | L77: 0.3 | M77: =Tienda!$K207-Tienda!$K207*Tienda!$L207 -> 145.755 | N77: Efectivo | O77: No | P77: 45427 | Q77: 0
A78: DEP-A0-1727 | B78: Femenino | C78: 20 | D78: =IF(Tabla1[[#This Row],[EDAD]]<=35,"Adultos jóvenes 18 - 35 años",IF(C78>=36,"Adultos mayores 36 años en adelante")) -> Adultos jóvenes 18 - 35 años | E78: Pantalón | F78: Rojo | G78: Adidas | H78: MER-A0-1727 | I78: 45429 | J78: =YEAR(Tabla1[[#This Row],[FECHA DE COMPRA]]) -> 2024 | K78: 53 | L78: 0.1 | M78: =Tienda!$K214-Tienda!$K214*Tienda!$L214 -> 111.591 | N78: Efectivo | O78: No | P78: 45429 | Q78: 0
A79: DEP-A0-0665 | B79: Femenino | C79: 31 | D79: =IF(Tabla1[[#This Row],[EDAD]]<=35,"Adultos jóvenes 18 - 35 años",IF(C79>=36,"Adultos mayores 36 años en adelante")) -> Adultos jóvenes 18 - 35 años | E79: Blusa | F79: Rojo | G79: Levis | H79: MER-A0-0665 | I79: 45429 | J79: =YEAR(Tabla1[[#This Row],[FECHA DE COMPRA]]) -> 2024 | K79: 79.96 | L79: 0.3 | M79: =Tienda!$K216-Tienda!$K216*Tienda!$L216 -> 80.65 | N79: Efectivo | O79: No | P79: 45429 | Q79: 0
A80: DEP-A0-0809 | B80: Femenino | C80: 30 | D80: =IF(Tabla1[[#This Row],[EDAD]]<=35,"Adultos jóvenes 18 - 35 años",IF(C80>=36,"Adultos mayores 36 años en adelante")) -> Adultos jóvenes 18 - 35 años | E80: Camisa | F80: Amarillo | G80: Puma | H80: MER-A0-0809 | I80: 45429 | J80: =YEAR(Tabla1[[#This Row],[FECHA DE COMPRA]]) -> 2024 | K80: 88.87 | L80: 0 | M80: =Tienda!$K217-Tienda!$K217*Tienda!$L217 -> 80.32 | N80: Efectivo | O80: No | P80: 45429 | Q80: 0
A81: DEP-A0-0707 | B81: Masculino | C81: 28 | D81: =IF(Tabla1[[#This Row],[EDAD]]<=35,"Adultos jóvenes 18 - 35 años",IF(C81>=36,"Adultos mayores 36 años en adelante")) -> Adultos jóvenes 18 - 35 años | E81: Zapatos | F81: Verde | G81: Zara | H81: MER-A0-0707 | I81: 45429 | J81: =YEAR(Tabla1[[#This Row],[FECHA DE COMPRA]]) -> 2024 | K81: 114.1 | L81: 0.2 | M81: =Tienda!$K218-Tienda!$K218*Tienda!$L218 -> 43.05 | N81: Efectivo | O81: No | P81: 45429 | Q81: 0
A82: DEP-A0-2267 | B82: Femenino | C82: 28 | D82: =IF(Tabla1[[#This Row],[EDAD]]<=35,"Adultos jóvenes 18 - 35 años",IF(C82>=36,"Adultos mayores 36 años en adelante")) -> Adultos jóvenes 18 - 35 años | E82: Vestido | F82: Verde | G82: Zara | H82: MER-A0-2267 | I82: 45430 | J82: =YEAR(Tabla1[[#This Row],[FECHA DE COMPRA]]) -> 2024 | K82: 150.36 | L82: 0.2 | M82: =Tienda!$K221-Tienda!$K221*Tienda!$L221 -> 128.7 | N82: Efectivo | O82: No | P82: 45430 | Q82: 0
A83: DEP-A0-4745 | B83: Femenino | C83: 24 | D83: =IF(Tabla1[[#This Row],[EDAD]]<=35,"Adultos jóvenes 18 - 35 años",IF(C83>=36,"Adultos mayores 36 años en adelante")) -> Adultos jóvenes 18 - 35 años | E83: Blusa | F83: Rojo | G83: Levis | H83: MER-A0-4745 | I83: 45432 | J83: =YEAR(Tabla1[[#This Row],[FECHA DE COMPRA]]) -> 2024 | K83: 77.54 | L83: 0.2 | M83: =Tienda!$K223-Tienda!$K223*Tienda!$L223 -> 61.32 | N83: Efectivo | O83: No | P83: 45432 | Q83: 0
A84: DEP-A0-4448 | B84: Femenino | C84: 29 | D84: =IF(Tabla1[[#This Row],[EDAD]]<=35,"Adultos jóvenes 18 - 35 años",IF(C84>=36,"Adultos mayores 36 años en adelante")) -> Adultos jóvenes 18 - 35 años | E84: Pantalón | F84: Amarillo | G84: Adidas | H84: MER-A0-4448 | I84: 45433 | J84: =YEAR(Tabla1[[#This Row],[FECHA DE COMPRA]]) -> 2024 | K84: 180.76 | L84: 0 | M84: =Tienda!$K225-Tienda!$K225*Tienda!$L225 -> 82.773 | N84: Efectivo | O84: No | P84: 45433 | Q84: 0
A85: DEP-A0-2240 | B85: Femenino | C85: 20 | D85: =IF(Tabla1[[#This Row],[EDAD]]<=35,"Adultos jóvenes 18 - 35 años",IF(C85>=36,"Adultos mayores 36 años en adelante")) -> Adultos jóvenes 18 - 35 años | E85: Blusa | F85: Blanco | G85: Puma | H85: MER-A0-2240 | I85: 45434 | J85: =YEAR(Tabla1[[#This Row],[FECHA DE COMPRA]]) -> 2024 | K85: 105.15 | L85: 0.1 | M85: =Tienda!$K226-Tienda!$K226*Tienda!$L226 -> 52.947 | N85: Efectivo | O85: No | P85: 45434 | Q85: 0
A86: DEP-A0-3071 | B86: Femenino | C86: 27 | D86: =IF(Tabla1[[#This Row],[EDAD]]<=35,"Adultos jóvenes 18 - 35 años",IF(C86>=36,"Adultos mayores 36 años en adelante")) -> Adultos jóvenes 18 - 35 años | E86: Falda | F86: Negro | G86: Zara | H86: MER-A0-3071 | I86: 45437 | J86: =YEAR(Tabla1[[#This Row],[FECHA DE COMPRA]]) -> 2024 | K86: 169.05 | L86: 0.2 | M86: =Tienda!$K233-Tienda!$K233*Tienda!$L233 -> 49.488 | N86: Efectivo | O86: No | P86: 45437 | Q86: 0
A87: DEP-A0-0821 | B87: Femenino | C87: 22 | D87: =IF(Tabla1[[#This Row],[EDAD]]<=35,"Adultos jóvenes 18 - 35 años",IF(C87>=36,"Adultos mayores 36 años en adelante")) -> Adultos jóvenes 18 - 35 años | E87: Camisa | F87: Verde | G87: Levis | H87: MER-A0-0821 | I87: 45439 | J87: =YEAR(Tabla1[[#This Row],[FECHA DE COMPRA]]) -> 2024 | K87: 66.28 | L87: 0 | M87: =Tienda!$K234-Tienda!$K234*Tienda!$L234 -> 9.576 | N87: Efectivo | O87: No | P87: 45439 | Q87: 0
A88: DEP-A0-1877 | B88: Masculino | C88: 20 | D88: =IF(Tabla1[[#This Row],[EDAD]]<=35,"Adultos jóvenes 18 - 35 años",IF(C88>=36,"Adultos mayores 36 años en adelante")) -> Adultos jóvenes 18 - 35 años | E88: Chaqueta | F88: Verde | G88: Tommy | H88: MER-A0-1877 | I88: 45440 | J88: =YEAR(Tabla1[[#This Row],[FECHA DE COMPRA]]) -> 2024 | K88: 84.27 | L88: 0.2 | M88: =Tienda!$K237-Tienda!$K237*Tienda!$L237 -> 170.685 | N88: Efectivo | O88: No | P88: 45440 | Q88: 0
A89: DEP-A0-2917 | B89: Femenino | C89: 20 | D89: =IF(Tabla1[[#This Row],[EDAD]]<=35,"Adultos jóvenes 18 - 35 años",IF(C89>=36,"Adultos mayores 36 años en adelante")) -> Adultos jóvenes 18 - 35 años | E89: Chaqueta | F89: Verde | G89: Zara | H89: MER-A0-2917 | I89: 45440 | J89: =YEAR(Tabla1[[#This Row],[FECHA DE COMPRA]]) -> 2024 | K89: 149.44 | L89: 0 | M89: =Tienda!$K239-Tienda!$K239*Tienda!$L239 -> 82.088 | N89: Efectivo | O89: No | P89: 45440 | Q89: 0
A90: DEP-A0-3557 | B90: Femenino | C90: 25 | D90: =IF(Tabla1[[#This Row],[EDAD]]<=35,"Adultos jóvenes 18 - 35 años",IF(C90>=36,"Adultos mayores 36 años en adelante")) -> Adultos jóvenes 18 - 35 años | E90: Blusa | F90: Rojo | G90: Zara | H90: MER-A0-3557 | I90: 45440 | J90: =YEAR(Tabla1[[#This Row],[FECHA DE COMPRA]]) -> 2024 | K90: 163.73 | L90: 0.2 | M90: =Tienda!$K240-Tienda!$K240*Tienda!$L240 -> 139.491 | N90: Efectivo | O90: No | P90: 45440 | Q90: 0
A91: DEP-A0-1040 | B91: Femenino | C91: 29 | D91: =IF(Tabla1[[#This Row],[EDAD]]<=35,"Adultos jóvenes 18 - 35 años",IF(C91>=36,"Adultos mayores 36 años en adelante")) -> Adultos jóvenes 18 - 35 años | E91: Chaqueta | F91: Gris | G91: Puma | H91: MER-A0-1040 | I91: 45441 | J91: =YEAR(Tabla1[[#This Row],[FECHA DE COMPRA]]) -> 2024 | K91: 120.91 | L91: 0.3 | M91: =Tienda!$K244-Tienda!$K244*Tienda!$L244 -> 113.59 | N91: Efectivo | O91: No | P91: 45441 | Q91: 0
A92: DEP-A0-3302 | B92: Femenino | C92: 34 | D92: =IF(Tabla1[[#This Row],[EDAD]]<=35,"Adultos jóvenes 18 - 35 años",IF(C92>=36,"Adultos mayores 36 años en adelante")) -> Adultos jóvenes 18 - 35 años | E92: Falda | F92: Gris | G92: Puma | H92: MER-A0-3302 | I92: 45442 | J92: =YEAR(Tabla1[[#This Row],[FECHA DE COMPRA]]) -> 2024 | K92: 108.21 | L92: 0.2 | M92: =Tienda!$K246-Tienda!$K246*Tienda!$L246 -> 80.736 | N92: Efectivo | O92: No | P92: 45442 | Q92: 0
A93: DEP-A0-4215 | B93: Masculino | C93: 20 | D93: =IF(Tabla1[[#This Row],[EDAD]]<=35,"Adultos jóvenes 18 - 35 años",IF(C93>=36,"Adultos mayores 36 años en adelante")) -> Adultos jóvenes 18 - 35 años | E93: Pantalón | F93: Negro | G93: Mango | H93: MER-A0-4215 | I93: 45442 | J93: =YEAR(Tabla1[[#This Row],[FECHA DE COMPRA]]) -> 2024 | K93: 112.8 | L93: 0.3 | M93: =Tienda!$K247-Tienda!$K247*Tienda!$L247 -> 68.908 | N93: Efectivo | O93: No | P93: 45442 | Q93: 0
A94: DEP-A0-1100 | B94: Masculino | C94: 26 | D94: =IF(Tabla1[[#This Row],[EDAD]]<=35,"Adultos jóvenes 18 - 35 años",IF(C94>=36,"Adultos mayores 36 años en adelante")) -> Adultos jóvenes 18 - 35 años | E94: Zapatos | F94: Verde | G94: Nike | H94: MER-A0-1100 | I94: 45442 | J94: =YEAR(Tabla1[[#This Row],[FECHA DE COMPRA]]) -> 2024 | K94: 170.73 | L94: 0.3 | M94: =Tienda!$K248-Tienda!$K248*Tienda!$L248 -> 111 | N94: Efectivo | O94: No | P94: 45442 | Q94: 0
A95: DEP-A0-4930 | B95: Femenino | C95: 22 | D95: =IF(Tabla1[[#This Row],[EDAD]]<=35,"Adultos jóvenes 18 - 35 años",IF(C95>=36,"Adultos mayores 36 años en adelante")) -> Adultos jóvenes 18 - 35 años | E95: Vestido | F95: Negro | G95: Puma | H95: MER-A0-4930 | I95: 45444 | J95: =YEAR(Tabla1[[#This Row],[FECHA DE COMPRA]]) -> 2024 | K95: 70.45 | L95: 0.2 | M95: =Tienda!$K252-Tienda!$K252*Tienda!$L252 -> 134.656 | N95: Efectivo | O95: No | P95: 45444 | Q95: 0
A96: DEP-A0-1621 | B96: Femenino | C96: 27 | D96: =IF(Tabla1[[#This Row],[EDAD]]<=35,"Adultos jóvenes 18 - 35 años",IF(C96>=36,"Adultos mayores 36 años en adelante")) -> Adultos jóvenes 18 - 35 años | E96: Vestido | F96: Verde | G96: Tommy | H96: MER-A0-1621 | I96: 45444 | J96: =YEAR(Tabla1[[#This Row],[FECHA DE COMPRA]]) -> 2024 | K96: 94.38 | L96: 0.1 | M96: =Tienda!$K253-Tienda!$K253*Tienda!$L253 -> 179.87 | N96: Efectivo | O96: No | P96: 45444 | Q96: 0
A97: DEP-A0-1307 | B97: Femenino | C97: 23 | D97: =IF(Tabla1[[#This Row],[EDAD]]<=35,"Adultos jóvenes 18 - 35 años",IF(C97>=36,"Adultos mayores 36 años en adelante")) -> Adultos jóvenes 18 - 35 años | E97: Chaqueta | F97: Gris | G97: Mango | H97: MER-A0-1307 | I97: 45634 | J97: =YEAR(Tabla1[[#This Row],[FECHA DE COMPRA]]) -> 2024 | K97: 128.55 | L97: 0.2 | M97: =Tienda!$K254-Tienda!$K254*Tienda!$L254 -> 147.82 | N97: Efectivo | O97: No | P97: 45444 | Q97: 0
A98: DEP-A0-3565 | B98: Femenino | C98: 27 | D98: =IF(Tabla1[[#This Row],[EDAD]]<=35,"Adultos jóvenes 18 - 35 años",IF(C98>=36,"Adultos mayores 36 años en adelante")) -> Adultos jóvenes 18 - 35 años | E98: Vestido | F98: Verde | G98: Levis | H98: MER-A0-3565 | I98: 45635 | J98: =YEAR(Tabla1[[#This Row],[FECHA DE COMPRA]]) -> 2024 | K98: 32.88 | L98: 0.2 | M98: =Tienda!$K260-Tienda!$K260*Tienda!$L260 -> 29.475 | N98: Efectivo | O98: No | P98: 45446 | Q98: 0
A99: DEP-A0-1523 | B99: Femenino | C99: 27 | D99: =IF(Tabla1[[#This Row],[EDAD]]<=35,"Adultos jóvenes 18 - 35 años",IF(C99>=36,"Adultos mayores 36 años en adelante")) -> Adultos jóvenes 18 - 35 años | E99: Falda | F99: Rojo | G99: Tommy | H99: MER-A0-1523 | I99: 45636 | J99: =YEAR(Tabla1[[#This Row],[FECHA DE COMPRA]]) -> 2024 | K99: 191.43 | L99: 0.1 | M99: =Tienda!$K263-Tienda!$K263*Tienda!$L263 -> 71.056 | N99: Efectivo | O99: No | P99: 45446 | Q99: 0
A100: DEP-A0-4106 | B100: Femenino | C100: 29 | D100: =IF(Tabla1[[#This Row],[EDAD]]<=35,"Adultos jóvenes 18 - 35 años",IF(C100>=36,"Adultos mayores 36 años en adelante")) -> Adultos jóvenes 18 - 35 años | E100: Pantalón | F100: Blanco | G100: Nike | H100: MER-A0-4106 | I100: 45636 | J100: =YEAR(Tabla1[[#This Row],[FECHA DE COMPRA]]) -> 2024 | K100: 60.48 | L100: 0.3 | M100: =Tienda!$K265-Tienda!$K265*Tienda!$L265 -> 98.308 | N100: Efectivo | O100: No | P100: 45447 | Q100: 0
...

Sheet Resumen Género
A1: Recomendación: Usar la función =CONTAR.SI.CONJUNTO()
A2: Género | B2: 2024 | C2: 2025
A3: Masculino | B3: =COUNTIFS(Tabla1[AÑO DE COMPRA],'Resumen Género'!B2,Tabla1[GENERO],'Resumen Género'!A3) -> 859 | C3: =COUNTIFS(Tabla1[AÑO DE COMPRA],'Resumen Género'!C2,Tabla1[GENERO],'Resumen Género'!A3) -> 511
A4: Femenino | B4: =COUNTIFS(Tabla1[AÑO DE COMPRA],'Resumen Género'!B2,Tabla1[GENERO],'Resumen Género'!A4) -> 2243 | C4: =COUNTIFS(Tabla1[AÑO DE COMPRA],'Resumen Género'!C2,Tabla1[GENERO],'Resumen Género'!A4) -> 1387
A5: Recomendación: Usar la función =PROMEDIO.SI()
A6: Tipo de pago | B6: Total a pagar
A7: Efectivo | B7: =AVERAGEIF(Tienda!N2:N5001,'Resumen Género'!A7,Tienda!M2:M5001) -> 94.120794
A8: Tarjeta de crédito | B8: =AVERAGEIF(Tienda!N2:N5001,'Resumen Género'!A8,Tienda!M2:M5001) -> 82.938656
A9: Tarjeta Deprati | B9: =AVERAGEIF(Tienda!N2:N5001,'Resumen Género'!A9,Tienda!M2:M5001) -> 94.799386
A10: Recomendación: Usar la función =CONTAR.SI()
A11: Clientes | B11: Edades
A12: Adultos jóvenes 18 - 35 años | B12: =COUNTIF(Tienda!C2:C5001,"<=35") -> 1856
A13: Adultos mayores 36 años en adelante | B13: =COUNTIF(Tienda!C2:C5001,">35") -> 3144
